experinet/__init__.py
experinet/_version.py
experinet/experiment.py
experinet/run.py
experinet-0.0.0.dist-info/METADATA
experinet-0.0.0.dist-info/RECORD
experinet-0.0.0.dist-info/WHEEL
experinet-0.0.0.dist-info/entry_points.txt
experinet-0.0.0.dist-info/top_level.txt
scripts/__init__.py
scripts/experinet_cli.py
