Metadata-Version: 2.1
Name: experinet
Version: 0.0.0
Summary: Network propagation models for networkx.
Home-page: https://github.com/shaypal5/experinet
Author: Shay Palachy
Author-email: shay.palachy@gmail.com
License: MIT
Platform: UNKNOWN
Classifier: Development Status :: 4 - Beta
Classifier: License :: OSI Approved :: MIT License
Classifier: Programming Language :: Python
Classifier: Programming Language :: Python :: 3.5
Classifier: Programming Language :: Python :: 3.6
Classifier: Topic :: Software Development :: Libraries
Classifier: Topic :: Software Development :: Libraries :: Python Modules
Classifier: Intended Audience :: Developers
Requires-Python: >=3.5
Provides-Extra: test
Requires-Dist: click
Requires-Dist: networkx
Provides-Extra: test
Requires-Dist: pytest; extra == 'test'
Requires-Dist: coverage; extra == 'test'
Requires-Dist: pytest-cov; extra == 'test'
Requires-Dist: collective.checkdocs; extra == 'test'
Requires-Dist: pygments; extra == 'test'
Requires-Dist: click; extra == 'test'
Requires-Dist: networkx; extra == 'test'
